{"stats":{"minecraft:custom":{"minecraft:jump":6,"minecraft:time_since_rest":2493,"minecraft:leave_game":1,"minecraft:crouch_one_cm":4,"minecraft:walk_on_water_one_cm":1066,"minecraft:sprint_one_cm":162,"minecraft:play_time":2493,"minecraft:time_since_death":2493,"minecraft:walk_one_cm":2024,"minecraft:sneak_time":188,"minecraft:total_world_time":2510,"minecraft:walk_under_water_one_cm":1610,"minecraft:swim_one_cm":888,"minecraft:fly_one_cm":20631},"minecraft:used":{"minecraft:lever":4,"mfff:forceprojector":1}},"DataVersion":3700}